README.rst
setup.py
rasmipy/__init__.py
rasmipy/rest_service.py
rasmipy.egg-info/PKG-INFO
rasmipy.egg-info/SOURCES.txt
rasmipy.egg-info/dependency_links.txt
rasmipy.egg-info/entry_points.txt
rasmipy.egg-info/requires.txt
rasmipy.egg-info/top_level.txt