Metadata-Version: 1.2
Name: rasmipy
Version: 0.2
Summary: Reduce Arabic strings to their rasm, ie remove vocalization and other diacritics.
Home-page: https://github.com/telota/rasmipy
Author: Oliver Pohl, Frank Sachsenheim
Author-email: telota@bbaw.de
License: LGPLv3
Platform: UNKNOWN
Classifier: Development Status :: 4 - Beta
Classifier: Intended Audience :: Developers
Classifier: License :: OSI Approved :: GNU General Public License v3 or later (GPLv3+)
Classifier: Natural Language :: Arabic
Classifier: Programming Language :: Python :: 3 :: Only
Classifier: Topic :: Text Processing :: Filters
Classifier: Topic :: Text Processing :: Linguistic
Requires-Python: >=3
